sensors.py
sensors.py-2.0.dist-info/LICENSE
sensors.py-2.0.dist-info/METADATA
sensors.py-2.0.dist-info/WHEEL
sensors.py-2.0.dist-info/top_level.txt
sensors.py-2.0.dist-info/RECORD
