Metadata-Version: 2.1
Name: sensors.py
Version: 2.0
Summary: Python bindings for libsensors3
Home-page: https://github.com/paroj/sensors.py
Author: Pavel Rojtberg
License: LGPLv2
License-File: LICENSE
